aio_georss_gdacs/__init__.py
aio_georss_gdacs/__version__.py
aio_georss_gdacs/consts.py
aio_georss_gdacs/feed.py
aio_georss_gdacs/feed_entry.py
aio_georss_gdacs/feed_manager.py
aio_georss_gdacs-0.10.dist-info/LICENSE
aio_georss_gdacs-0.10.dist-info/METADATA
aio_georss_gdacs-0.10.dist-info/WHEEL
aio_georss_gdacs-0.10.dist-info/top_level.txt
aio_georss_gdacs-0.10.dist-info/RECORD
