Metadata-Version: 2.1
Name: aio-georss-gdacs
Version: 0.10
Summary: An async GeoRSS client library for GDACS feeds.
Home-page: https://github.com/exxamalte/python-aio-georss-gdacs
Author: Malte Franken
Author-email: coding@subspace.de
License: Apache-2.0
Classifier: Programming Language :: Python :: 3.9
Classifier: Programming Language :: Python :: 3.10
Classifier: Programming Language :: Python :: 3.11
Classifier: Programming Language :: Python :: 3.12
Classifier: License :: OSI Approved :: Apache Software License
Classifier: Operating System :: OS Independent
License-File: LICENSE
